databricks_cli/__init__.py
databricks_cli/cli.py
databricks_cli/click_types.py
databricks_cli/utils.py
databricks_cli/version.py
databricks_cli/cluster_policies/__init__.py
databricks_cli/cluster_policies/api.py
databricks_cli/cluster_policies/cli.py
databricks_cli/clusters/__init__.py
databricks_cli/clusters/api.py
databricks_cli/clusters/cli.py
databricks_cli/configure/__init__.py
databricks_cli/configure/cli.py
databricks_cli/configure/config.py
databricks_cli/configure/provider.py
databricks_cli/dbfs/__init__.py
databricks_cli/dbfs/api.py
databricks_cli/dbfs/cli.py
databricks_cli/dbfs/dbfs_path.py
databricks_cli/dbfs/exceptions.py
databricks_cli/groups/__init__.py
databricks_cli/groups/api.py
databricks_cli/groups/cli.py
databricks_cli/instance_pools/__init__.py
databricks_cli/instance_pools/api.py
databricks_cli/instance_pools/cli.py
databricks_cli/jobs/__init__.py
databricks_cli/jobs/api.py
databricks_cli/jobs/cli.py
databricks_cli/libraries/__init__.py
databricks_cli/libraries/api.py
databricks_cli/libraries/cli.py
databricks_cli/pipelines/__init__.py
databricks_cli/pipelines/api.py
databricks_cli/pipelines/cli.py
databricks_cli/repos/__init__.py
databricks_cli/repos/api.py
databricks_cli/repos/cli.py
databricks_cli/runs/__init__.py
databricks_cli/runs/api.py
databricks_cli/runs/cli.py
databricks_cli/sdk/__init__.py
databricks_cli/sdk/api_client.py
databricks_cli/sdk/service.py
databricks_cli/sdk/version.py
databricks_cli/secrets/__init__.py
databricks_cli/secrets/api.py
databricks_cli/secrets/cli.py
databricks_cli/stack/__init__.py
databricks_cli/stack/api.py
databricks_cli/stack/cli.py
databricks_cli/stack/exceptions.py
databricks_cli/tokens/__init__.py
databricks_cli/tokens/api.py
databricks_cli/tokens/cli.py
databricks_cli/unity_catalog/__init__.py
databricks_cli/unity_catalog/api.py
databricks_cli/unity_catalog/catalog_cli.py
databricks_cli/unity_catalog/cli.py
databricks_cli/unity_catalog/cred_cli.py
databricks_cli/unity_catalog/delta_sharing_cli.py
databricks_cli_uc-0.16.3.13.dist-info/LICENSE.txt
databricks_cli_uc-0.16.3.13.dist-info/METADATA
databricks_cli_uc-0.16.3.13.dist-info/NOTICE.txt
databricks_cli_uc-0.16.3.13.dist-info/WHEEL
databricks_cli_uc-0.16.3.13.dist-info/entry_points.txt
databricks_cli_uc-0.16.3.13.dist-info/top_level.txt
databricks_cli_uc-0.16.3.13.dist-info/RECORD
