Metadata-Version: 2.1
Name: databricks-cli-uc
Version: 0.16.3.13
Summary: A command line interface for Databricks with Unity Catalog extensions
Home-page: https://github.com/databricks/databricks-cli
Author: Adam Cain
Author-email: adam.cain@databricks.com
License: Apache License 2.0
Keywords: databricks cli
Platform: UNKNOWN
Classifier: Intended Audience :: Developers
Classifier: Intended Audience :: System Administrators
Classifier: Programming Language :: Python :: 2.7
Classifier: Programming Language :: Python :: 3.6
Classifier: License :: OSI Approved :: Apache Software License
Requires-Dist: click (>=6.7)
Requires-Dist: requests (>=2.17.3)
Requires-Dist: tabulate (>=0.7.7)
Requires-Dist: six (>=1.10.0)
Requires-Dist: configparser (>=0.3.5) ; python_version < "3.6"
